crow/__init__.py
crow/agent/__init__.py
crow/agent/__main__.py
crow/agent/acp_server.py
crow/agent/cli.py
crow/agent/config.py
crow/agent/openhands_acp_poc.py
crow/agent/hooks/post_tool_use_acp.py
crow/editor/README.md
crow/mcp/search.py
crow_ai-0.1.2.dist-info/METADATA
crow_ai-0.1.2.dist-info/WHEEL
crow_ai-0.1.2.dist-info/entry_points.txt
crow_ai-0.1.2.dist-info/RECORD
