Metadata-Version: 2.4
Name: crow-ai
Version: 0.1.2
Summary: Add your description here
Requires-Python: >=3.12
Requires-Dist: agent-client-protocol
Requires-Dist: aiofiles>=25.1.0
Requires-Dist: ipython>=9.9.0
Requires-Dist: markdownify>=1.2.2
Requires-Dist: openai>=2.14.0
Requires-Dist: openhands-sdk
Requires-Dist: openhands-tools
Requires-Dist: python-dotenv>=1.2.1
Requires-Dist: requests>=2.32.5
